[
  {
    "id": 1,
    "name": "Rosetta Stone",
    "origin": "Egypt",
    "date": "196 BC",
    "description": "The key that unlocked ancient Egyptian hieroglyphs.",
    "room": "Room 4",
    "british": false,
    "contested": false,
    "image": "./assets/images/Rosetta-Stone-in-situ.webp"
  },
  {
    "id": 2,
    "name": "Sophilos Vase",
    "origin": "Greece",
    "date": "c. 580 BC",
    "description": "One of the earliest signed works in Western art.",
    "room": "Room 13",
    "british": false,
    "contested": false,
    "image": "./assets/images/sophilos-dinos-1000.png"
  },
  {
    "id": 3,
    "name": "Parthenon Sculptures",
    "origin": "Greece",
    "date": "438–432 BC",
    "description": "Greece has formally requested their return since 1983.",
    "room": "Room 18",
    "british": false,
    "contested": true,
    "image": "./assets/images/Parthenon-east-pediment-1000x782.jpg"
  },
  {
    "id": 4,
    "name": "Crouching Venus",
    "origin": "Italy (Roman)",
    "date": "2nd century AD",
    "description": "A Roman copy of a lost Greek original of Aphrodite.",
    "room": "Room 23",
    "british": false,
    "contested": false,
    "image": "./assets/images/Crouching-Venus-861x1000.jpg"
  },
  {
    "id": 5,
    "name": "Bust of Ramesses the Great",
    "origin": "Egypt",
    "date": "1279–1213 BC",
    "description": "A colossal 7.5-tonne granite bust from ancient Thebes.",
    "room": "Room 4",
    "british": false,
    "contested": false,
    "image": "./assets/images/bust-ramesses-1000.jpg"
  },
  {
    "id": 6,
    "name": "Ife Head",
    "origin": "Nigeria",
    "date": "1300–early 1400s",
    "description": "Brass head of an Ooni, sacred king of the Kingdom of Ife.",
    "room": "Room 25",
    "british": false,
    "contested": false,
    "image": "./assets/images/Brass-Ife-head-769x1024.png"
  },
  {
    "id": 7,
    "name": "Tree of Life",
    "origin": "Mozambique",
    "date": "2004",
    "description": "Made from decommissioned civil war weapons by four Mozambican artists.",
    "room": "Room 25",
    "british": false,
    "contested": false,
    "image": "./assets/images/Room-25-Africa-Gallery-tree-of-life.jpg"
  },
  {
    "id": 8,
    "name": "Akan Drum",
    "origin": "Ghana",
    "date": "18th century",
    "description": "The earliest African-American object in the museum.",
    "room": "Room 26",
    "british": false,
    "contested": false,
    "image": "./assets/images/akan-drum-west-africa-1000.jpg"
  },
  {
    "id": 9,
    "name": "Aztec Serpent",
    "origin": "Mexico",
    "date": "1400–1521",
    "description": "A double-headed serpent made from 2,000 pieces of turquoise.",
    "room": "Room 27",
    "british": false,
    "contested": false,
    "image": "./assets/images/A-turquoise-two-headed-serpent-1000x500.jpg"
  },
  {
    "id": 10,
    "name": "Piranesi Vase",
    "origin": "Italy (Roman)",
    "date": "2nd century AD, restored 18th c.",
    "description": "A 2.7m marble vase assembled from classical fragments.",
    "room": "Room 1",
    "british": false,
    "contested": false,
    "image": "./assets/images/Enlightenment-Gallery-Piranesi-vase-1304x1304.jpg"
  },
  {
    "id": 11,
    "name": "Haida House Pole",
    "origin": "Canada",
    "date": "c. 1850",
    "description": "A 15m totem pole from the Haida village of Kayang, BC.",
    "room": "Great Court",
    "british": false,
    "contested": false,
    "image": "./assets/images/Haida-totem-pole-1000x1884.jpg"
  },
  {
    "id": 12,
    "name": "Hoa Hakananai'a",
    "origin": "Rapa Nui (Easter Island)",
    "date": "c. 1000–1200 AD",
    "description": "A basalt moai — a living face of the ancestors. Return formally requested 2018.",
    "room": "Room 24",
    "british": false,
    "contested": true,
    "image": "./assets/images/Hoa_Hakananaia_Room_24_British_Museum_2_0.jpg"
  }
]
